resu/__init__.py
resu/resu.py
resu-0.2.2.dist-info/LICENSE
resu-0.2.2.dist-info/WHEEL
resu-0.2.2.dist-info/METADATA
resu-0.2.2.dist-info/RECORD
