Metadata-Version: 2.1
Name: resu
Version: 0.2.2
Summary: Resume your progress in any python loop
Author-email: Alyetama <malyetama@pm.me>
Classifier: License :: OSI Approved :: MIT License
Requires-Dist: tqdm
Project-URL: Home, https://github.com/Alyetama/resu
